ubitlogger/__init__.py
ubitlogger/cli.py
ubitlogger/data_receiver.py
ubitlogger/read_sensor.py
ubitlogger-0.5.2.dist-info/LICENSE
ubitlogger-0.5.2.dist-info/METADATA
ubitlogger-0.5.2.dist-info/WHEEL
ubitlogger-0.5.2.dist-info/entry_points.txt
ubitlogger-0.5.2.dist-info/top_level.txt
ubitlogger-0.5.2.dist-info/RECORD
