Metadata-Version: 2.1
Name: ubitlogger
Version: 0.5.2
Summary: A micro:bit serial port logger
Author-email: p4irin <p4irin.github.io@gmail.com>
Project-URL: Homepage, https://github.com/p4irin/ubitlogger
Project-URL: Bug Tracker, https://github.com/p4irin/ubitlogger/issues
Keywords: microbit,microbit-v1,data-logger,serial-port-listener
Classifier: Programming Language :: Python :: 3
Classifier: Programming Language :: Python :: 3.8
Classifier: Programming Language :: Python :: 3.9
Classifier: Programming Language :: Python :: 3.10
Classifier: Operating System :: POSIX :: Linux
Classifier: Intended Audience :: Developers
Classifier: Topic :: Software Development :: Libraries :: Python Modules
Classifier: License :: OSI Approved :: MIT License
Requires-Python: >=3.8.10
License-File: LICENSE
Requires-Dist: pyserial >=3.5
Requires-Dist: uflash >=2.0.0
Provides-Extra: dev
Requires-Dist: bumpver >=2023.1126 ; extra == 'dev'
Requires-Dist: ubitlogger[lint] ; extra == 'dev'
Requires-Dist: ubitlogger[test] ; extra == 'dev'
Requires-Dist: ubitlogger[package] ; extra == 'dev'
Provides-Extra: lint
Requires-Dist: mypy >=1.9.0 ; extra == 'lint'
Requires-Dist: ruff >=0.3.4 ; extra == 'lint'
Provides-Extra: package
Requires-Dist: build ==0.10.0 ; extra == 'package'
Requires-Dist: twine >=4.0.2 ; extra == 'package'
Provides-Extra: test
Requires-Dist: pytest >=8.1.1 ; extra == 'test'
Requires-Dist: pytest-cov >=4.1.0 ; extra == 'test'
